bayes_jones/__init__.py
bayes_jones/common.py
bayes_jones/parameter_estimation.py
bayes_jones/types.py
bayes_jones/utils.py
bayes_jones/tests/__init__.py
bayes_jones/tests/conftest.py
bayes_jones/tests/test_parameter_estimation.py
bayes_jones-0.0.1.dist-info/LICENSE
bayes_jones-0.0.1.dist-info/METADATA
bayes_jones-0.0.1.dist-info/WHEEL
bayes_jones-0.0.1.dist-info/top_level.txt
bayes_jones-0.0.1.dist-info/RECORD
