Metadata-Version: 2.1
Name: bayes-jones
Version: 0.0.1
Summary: Bayesian inference of Jones matrices.
Home-page: https://github.com/joshuaalbert/bayes_jones
Author: Joshua G. Albert
Author-email: albert@strw.leidenuniv.nl
Classifier: Programming Language :: Python :: 3
Classifier: License :: OSI Approved :: Apache Software License
Classifier: Operating System :: OS Independent
Requires-Python: >=3.8
License-File: LICENSE
Requires-Dist: jax
Requires-Dist: jaxlib
Requires-Dist: chex
Requires-Dist: typing-extensions
Requires-Dist: matplotlib
Requires-Dist: numpy
Requires-Dist: pytest
Requires-Dist: scipy
Requires-Dist: tensorflow-probability
Requires-Dist: tqdm
Requires-Dist: dm-haiku
Requires-Dist: optax
Requires-Dist: jaxns >=2.3.0
